precreal/__init__.py
precreal/algorithms.py
precreal/precreal.py
precreal/test.py
precreal-1.0.2.dist-info/METADATA
precreal-1.0.2.dist-info/WHEEL
precreal-1.0.2.dist-info/entry_points.txt
precreal-1.0.2.dist-info/top_level.txt
precreal-1.0.2.dist-info/RECORD
