Metadata-Version: 2.1
Name: precreal
Version: 1.0.2
Summary: A package providing a fraction-based Real class that allows you to do exact real arithmetic, along with some algorithms
Home-page: https://github.com/none-None1/precreal
Author: None1
Keywords: arithmetic,calculating,real number
Requires-Python: >=3
